CHANGES.txt
bootstrap.py
buildout.cfg
setup.py
src/z3c/__init__.py
src/z3c.noop.egg-info/PKG-INFO
src/z3c.noop.egg-info/SOURCES.txt
src/z3c.noop.egg-info/dependency_links.txt
src/z3c.noop.egg-info/namespace_packages.txt
src/z3c.noop.egg-info/not-zip-safe
src/z3c.noop.egg-info/requires.txt
src/z3c.noop.egg-info/top_level.txt
src/z3c/noop/README.txt
src/z3c/noop/__init__.py
src/z3c/noop/configure.zcml
src/z3c/noop/ftesting.zcml
src/z3c/noop/tests.py
src/z3c/noop/traverser.py