Metadata-Version: 1.0
Name: z3c.noop
Version: 1.0
Summary: z3c.noop provides traverser that simply skips a path element, so /foo/++noop++qux/bar is equivalent to /foo/bar.
Home-page: http://pypi.python.org/pypi/z3c.noop
Author: Wolfgang Schnerring
Author-email: ws@gocept.com
License: ZPL 2.1
Platform: UNKNOWN
Classifier: Intended Audience :: Developers
Classifier: License :: OSI Approved :: Zope Public License
Classifier: Programming Language :: Python
Classifier: Operating System :: OS Independent
Classifier: Framework :: Zope3
